winrmlib
